duckdantic/__init__.py
duckdantic/algebra.py
duckdantic/cache.py
duckdantic/compare.py
duckdantic/comparer.py
duckdantic/extras.py
duckdantic/fields.py
duckdantic/match.py
duckdantic/models.py
duckdantic/naming.py
duckdantic/normalize.py
duckdantic/policy.py
duckdantic/registry.py
duckdantic/shapes.py
duckdantic/traits.py
duckdantic/adapters/__init__.py
duckdantic/adapters/abc.py
duckdantic/providers/attrs.py
duckdantic/providers/base.py
duckdantic/providers/dataclass.py
duckdantic/providers/mapping.py
duckdantic/providers/plainclass.py
duckdantic/providers/pydantic_v2.py
duckdantic/providers/typeddict.py
duckdantic-1.1.1.dist-info/METADATA
duckdantic-1.1.1.dist-info/WHEEL
duckdantic-1.1.1.dist-info/licenses/LICENSE.txt
duckdantic-1.1.1.dist-info/RECORD
