Metadata-Version: 2.4
Name: duckdantic
Version: 1.1.1
Summary: Flexible structural typing and runtime validation for Python
Project-URL: Documentation, https://duckdantic.readthedocs.io/
Project-URL: Repository, https://github.com/pr1m8/duckdantic
Project-URL: Issues, https://github.com/pr1m8/duckdantic/issues
Project-URL: Changelog, https://github.com/pr1m8/duckdantic/blob/main/CHANGELOG.md
Project-URL: PyPI, https://pypi.org/project/duckdantic/
Author-email: duckdantic <william.astley@algebraicwealth.com>
License-Expression: MIT
License-File: LICENSE.txt
Keywords: duck-typing,pydantic,runtime-types,structural-typing,validation
Classifier: Development Status :: 4 - Beta
Classifier: Programming Language :: Python
Classifier: Programming Language :: Python :: 3.12
Classifier: Programming Language :: Python :: Implementation :: CPython
Classifier: Programming Language :: Python :: Implementation :: PyPy
Classifier: Topic :: Software Development :: Libraries :: Python Modules
Classifier: Topic :: Utilities
Classifier: Typing :: Typed
Requires-Python: >=3.12
Requires-Dist: typing-extensions>=4.5.0; python_version < '3.11'
Provides-Extra: all
Requires-Dist: pydantic>=2.0.0; extra == 'all'
Provides-Extra: docs
Requires-Dist: mkdocs-material>=9.0.0; extra == 'docs'
Requires-Dist: mkdocs>=1.5.0; extra == 'docs'
Requires-Dist: pymdown-extensions>=10.0; extra == 'docs'
Provides-Extra: pydantic
Requires-Dist: pydantic>=2.0.0; extra == 'pydantic'
